CHANGES.txt
MANIFEST.in
README.txt
setup.cfg
setup.py
afpy/__init__.py
afpy.ldap.egg-info/PKG-INFO
afpy.ldap.egg-info/SOURCES.txt
afpy.ldap.egg-info/dependency_links.txt
afpy.ldap.egg-info/entry_points.txt
afpy.ldap.egg-info/namespace_packages.txt
afpy.ldap.egg-info/not-zip-safe
afpy.ldap.egg-info/requires.txt
afpy.ldap.egg-info/top_level.txt
afpy/ldap/__init__.py
afpy/ldap/auth.py
afpy/ldap/authafpy.py
afpy/ldap/authbasic.py
afpy/ldap/connection.py
afpy/ldap/custom.py
afpy/ldap/forms.py
afpy/ldap/gawelorg.py
afpy/ldap/node.py
afpy/ldap/schema.py
afpy/ldap/scripts.py
afpy/ldap/test_auth.py
afpy/ldap/testing.py
afpy/ldap/tests.py
afpy/ldap/utils.py
afpy/ldap/ldaputil/__init__.py
afpy/ldap/ldaputil/base.py
afpy/ldap/ldaputil/modlist2.py
afpy/ldap/ldaputil/passwd.py
afpy/ldap/ldaputil/schema.py
docs/index.txt
docs/install.txt
docs/shell.txt
docs/testing.txt