Metadata-Version: 1.0
Name: afpy.ldap
Version: 1.0
Summary: This module provide an easy way to deal with ldap stuff in python.
Home-page: http://hg.afpy.org/gawel/afpy.ldap/
Author: Gael Pasgrimaud
Author-email: gael@gawel.org
License: MIT
Keywords: ldap repoze what
Platform: UNKNOWN
Classifier: Programming Language :: Python
Classifier: Topic :: Software Development :: Libraries :: Python Modules
Classifier: Topic :: Internet :: WWW/HTTP :: WSGI :: Middleware
